{"database/%E5%B0%BE%E9%9A%8F%E9%97%AD%E5%8C%85.md":["database/%E5%B0%BE%E9%9A%8F%E9%97%AD%E5%8C%85.md"],"database/%E8%87%AA%E5%8A%A8%E9%97%AD%E5%8C%85.md":["database/%E8%87%AA%E5%8A%A8%E9%97%AD%E5%8C%85.md"],"database/%E9%80%83%E9%80%B8%E9%97%AD%E5%8C%85.md":["database/%E9%80%83%E9%80%B8%E9%97%AD%E5%8C%85.md"],"database/%E9%97%AD%E5%8C%85%E4%BC%98%E5%8C%96.md":["database/%E9%97%AD%E5%8C%85%E4%BC%98%E5%8C%96.md"],"database/FlutterSksl%E4%BC%98%E5%8C%96.md":["database/FlutterSksl%E4%BC%98%E5%8C%96.md"],"database/swift_concurrency.md":["database/swift_concurrency.md"],"packages/cupertino_icons/assets/CupertinoIcons.ttf":["packages/cupertino_icons/assets/CupertinoIcons.ttf"]}